flops_profiler/__init__.py
flops_profiler/__version__.py
flops_profiler/profiler.py
flops_profiler/requirements.txt
flops_profiler-0.1.2.dist-info/LICENSE
flops_profiler-0.1.2.dist-info/METADATA
flops_profiler-0.1.2.dist-info/WHEEL
flops_profiler-0.1.2.dist-info/RECORD
