Metadata-Version: 2.1
Name: flops-profiler
Version: 0.1.2
Summary: Measures the parameters, latency, and floating-point operations of PyTorch model.
Author: Cheng Li
Author-email: pistasable@gmail.com
Requires-Python: >=3.8,<4.0
Classifier: Programming Language :: Python :: 3
Classifier: Programming Language :: Python :: 3.8
Classifier: Programming Language :: Python :: 3.9
Classifier: Programming Language :: Python :: 3.10
Classifier: Programming Language :: Python :: 3.11
Requires-Dist: importlib-metadata (>=6.0.0,<7.0.0)
